sharedcloud_cli/__init__.py
sharedcloud_cli/config.py
sharedcloud_cli/constants.py
sharedcloud_cli/main.py
sharedcloud_cli/mappers.py
sharedcloud_cli/utils.py
sharedcloud_cli/validators.py
sharedcloud_cli/cli/__init__.py
sharedcloud_cli/cli/account.py
sharedcloud_cli/cli/function.py
sharedcloud_cli/cli/gpu.py
sharedcloud_cli/cli/image.py
sharedcloud_cli/cli/instance.py
sharedcloud_cli/cli/job.py
sharedcloud_cli/cli/login.py
sharedcloud_cli/cli/logout.py
sharedcloud_cli/cli/offer.py
sharedcloud_cli/cli/run.py
sharedcloud_cli/cli/version.py
sharedcloud_cli-0.0.5.dist-info/METADATA
sharedcloud_cli-0.0.5.dist-info/RECORD
sharedcloud_cli-0.0.5.dist-info/WHEEL
sharedcloud_cli-0.0.5.dist-info/entry_points.txt
sharedcloud_cli-0.0.5.dist-info/top_level.txt
tests/__init__.py
tests/constants.py
tests/test_change_password.py
tests/test_clean_image.py
tests/test_create_account.py
tests/test_create_function.py
tests/test_create_instance.py
tests/test_create_run.py
tests/test_delete_account.py
tests/test_delete_function.py
tests/test_delete_instance.py
tests/test_delete_run.py
tests/test_download_image.py
tests/test_list_account.py
tests/test_list_functions.py
tests/test_list_gpus.py
tests/test_list_images.py
tests/test_list_jobs.py
tests/test_list_offers.py
tests/test_list_runs.py
tests/test_login.py
tests/test_logout.py
tests/test_start_instance.py
tests/test_start_instance_with_below_ask_price_jobs.py
tests/test_start_instance_with_failed_jobs.py
tests/test_start_instance_with_successful_jobs.py
tests/test_start_instance_with_timeout_jobs.py
tests/test_update_account.py
tests/test_update_all_images.py
tests/test_update_function.py
tests/test_update_instance.py
tests/test_utils.py
tests/test_version.py
tests/files/__init__.py
tests/files/func_python36.py
tests/files/func_timeout_python36.py
tests/files/invalid_func_python36.py
