Metadata-Version: 2.1
Name: sharedcloud-cli
Version: 0.0.5
Summary: Command Line Interface (CLI) for Sharedcloud.
Home-page: https://github.com/sharedcloud/sharedcloud-cli
Author: Sharedcloud
Author-email: admin@sharedcloud.io
Maintainer: Sharedcloud
Maintainer-email: admin@sharedcloud.io
License: MIT
Keywords: sharedcloud,cloud,computing,development,gpu,cpu,deep-learning,machine-learning,data-science,neural-networks,artificial-intelligence,ai,reinforcement-learning,devops
Platform: any
Classifier: Programming Language :: Python
Classifier: Operating System :: OS Independent
Classifier: Intended Audience :: Developers
Classifier: Intended Audience :: Science/Research
Classifier: Topic :: Scientific/Engineering :: Artificial Intelligence
Requires-Dist: click (==6.7)
Requires-Dist: requests (==2.19.1)
Requires-Dist: tabulate (==0.8.2)
Requires-Dist: timeago (==1.0.8)
